embs/__init__.py
embs/embs.py
embs-0.1.8.dist-info/LICENSE
embs-0.1.8.dist-info/METADATA
embs-0.1.8.dist-info/WHEEL
embs-0.1.8.dist-info/RECORD
