Metadata-Version: 2.1
Name: embs
Version: 0.1.8
Summary: Embs is a lightweight Python toolkit for document retrieval, embedding generation, and ranking—ideal for RAG-based AI, chatbots, and search systems with caching support.
Author: Hieu Lam
Author-email: lamhieu.vk@gmail.com
Requires-Python: >=3.10,<4.0
Classifier: Programming Language :: Python :: 3
Classifier: Programming Language :: Python :: 3.10
Classifier: Programming Language :: Python :: 3.11
Classifier: Programming Language :: Python :: 3.12
Classifier: Programming Language :: Python :: 3.13
Requires-Dist: aiohttp (>=3.8.4,<4.0.0)
Requires-Dist: duckduckgo-search (>=7.1.1,<8.0.0)
Requires-Dist: numpy (>=1,<2)
Requires-Dist: pytest (>=8.3.4,<9.0.0)
Requires-Dist: pytest-asyncio (>=0.25.2,<0.26.0)
